async_steam/__init__.py
async_steam/apps.py
async_steam/client.py
async_steam/constants.py
async_steam/steam.py
async_steam/users.py
async_steam/utils.py
async_python_async_steam_api-1.0.0.dist-info/LICENCE
async_python_async_steam_api-1.0.0.dist-info/METADATA
async_python_async_steam_api-1.0.0.dist-info/WHEEL
async_python_async_steam_api-1.0.0.dist-info/top_level.txt
async_python_async_steam_api-1.0.0.dist-info/RECORD
