Metadata-Version: 2.1
Name: async-python-async_steam-api
Version: 1.0.0
Summary: Async Python Client wrapper for Steam API
Home-page: https://github.com/deivit24/steam-python-sdk
Author: David Salazar
Author-email: david.asal@hotmail.com
License: MIT
Keywords: async_steam,steamapi,async_steam community,api
Classifier: Development Status :: 4 - Beta
Classifier: Intended Audience :: Developers
Classifier: License :: OSI Approved :: MIT License
Classifier: Operating System :: OS Independent
Classifier: Programming Language :: Python :: 3
Classifier: Programming Language :: Python :: 3.9
Classifier: Programming Language :: Python :: 3.10
Classifier: Programming Language :: Python :: 3.11
Classifier: Programming Language :: Python
License-File: LICENCE
Requires-Dist: beautifulsoup4
Requires-Dist: aiohttp
